app/__init__.py
app/args.py
app/ip_info.py
app/main.py
app/print_table.py
app/query_normalisation.py
ipilot-1.8.15.dist-info/METADATA
ipilot-1.8.15.dist-info/WHEEL
ipilot-1.8.15.dist-info/entry_points.txt
ipilot-1.8.15.dist-info/RECORD
