Metadata-Version: 2.1
Name: ipilot
Version: 1.8.15
Summary: IP Information Lookup Tool
Author-Email: Luke Tainton <luke@tainton.uk>
Requires-Python: <4.0,>=3.11
Requires-Dist: astroid==3.3.11
Requires-Dist: attrs==25.3.0
Requires-Dist: certifi==2025.8.3
Requires-Dist: charset-normalizer==3.4.3
Requires-Dist: click==8.3.0
Requires-Dist: dill==0.4.0
Requires-Dist: exceptiongroup==1.3.0
Requires-Dist: idna==3.10
Requires-Dist: iniconfig==2.1.0
Requires-Dist: lazy-object-proxy==1.12.0
Requires-Dist: mccabe==0.7.0
Requires-Dist: mypy-extensions==1.1.0
Requires-Dist: packaging==25.0
Requires-Dist: pathspec==0.12.1
Requires-Dist: platformdirs==4.4.0
Requires-Dist: pluggy==1.6.0
Requires-Dist: py==1.11.0
Requires-Dist: pyparsing==3.2.5
Requires-Dist: requests==2.32.5
Requires-Dist: six==1.17.0
Requires-Dist: tabulate==0.9.0
Requires-Dist: tomli==2.2.1
Requires-Dist: tomlkit==0.13.3
Requires-Dist: urllib3==2.5.0
Requires-Dist: wrapt==1.17.3
